{"name":"ingresar a la aplicacion con credenciales","id":"iniciar-sesion-en-la-aplicacion-de-saucedemo;ingresar-a-la-aplicacion-con-credenciales","testSteps":[{"number":1,"description":"Given que el usuario ingrese a la pagina web","duration":6793,"startTime":"2023-04-02T21:54:00.660187700-06:00[America/Regina]","screenshots":[{"screenshot":"b57a1c1c9263c737475299786910a7907434ea511ddb81e9324af6d5f5a3dd88.png","timeStamp":1680494047452,"screenshotName":"b57a1c1c9263c737475299786910a7907434ea511ddb81e9324af6d5f5a3dd88.png"}],"result":"SUCCESS","precondition":false,"level":0},{"number":2,"description":"When el usuario ingrese las credenciales","duration":1310,"startTime":"2023-04-02T21:54:07.455799800-06:00[America/Regina]","screenshots":[{"screenshot":"b8990d3ddbb98ecbdbfb68c3b7ae507cb9241d060307e256cc73023820c13c7c.png","timeStamp":1680494048766,"screenshotName":"b8990d3ddbb98ecbdbfb68c3b7ae507cb9241d060307e256cc73023820c13c7c.png"}],"result":"SUCCESS","precondition":false,"level":0},{"number":3,"description":"And dar click en el boton de login","duration":373,"startTime":"2023-04-02T21:54:08.767056900-06:00[America/Regina]","screenshots":[{"screenshot":"46bb9caac413a9ca6d6bcd9d39113810f01ff121bd131e46a46469959685740b.png","timeStamp":1680494049140,"screenshotName":"46bb9caac413a9ca6d6bcd9d39113810f01ff121bd131e46a46469959685740b.png"}],"result":"SUCCESS","precondition":false,"level":0},{"number":4,"description":"Then validamos que estemos en la pagina principal \"Products\"","duration":177,"startTime":"2023-04-02T21:54:09.141074-06:00[America/Regina]","screenshots":[{"screenshot":"46bb9caac413a9ca6d6bcd9d39113810f01ff121bd131e46a46469959685740b.png","htmlSource":"pagesource10638089472952120798.html","timeStamp":1680494049159,"screenshotName":"46bb9caac413a9ca6d6bcd9d39113810f01ff121bd131e46a46469959685740b.png"}],"result":"SUCCESS","precondition":false,"level":0}],"userStory":{"id":"iniciar-sesion-en-la-aplicacion-de-saucedemo","storyName":"iniciar sesion en la aplicacion de saucedemo","displayName":"iniciar sesion en la aplicacion de saucedemo","path":"test_login.feature","type":"feature"},"featureTag":{"name":"iniciar sesion en la aplicacion de saucedemo","type":"feature","displayName":"iniciar sesion en la aplicacion de saucedemo"},"title":"ingresar a la aplicacion con credenciales","description":"","tags":[{"name":"iniciar sesion en la aplicacion de saucedemo","type":"feature","displayName":"iniciar sesion en la aplicacion de saucedemo"},{"name":"login","type":"tag","displayName":"login"}],"startTime":"2023-04-02T21:54:00.578406300-06:00[America/Regina]","duration":8743,"projectKey":"","sessionId":"07edfc7d9b4ecec9879117810e221c08","driver":"chrome","isManualTestingUpToDate":false,"manual":false,"testSource":"Cucumber","result":"SUCCESS"}